LICENSE
MANIFEST.in
VERSION
setup.py
dotdict/__init__.py
dotdict/structure.py
dotdict/version.py
flexible_dotdict.egg-info/PKG-INFO
flexible_dotdict.egg-info/SOURCES.txt
flexible_dotdict.egg-info/dependency_links.txt
flexible_dotdict.egg-info/top_level.txt